{"悪":{"kanji":"悪","level":4,"reading":["アク","オ","わる-い"],"meaning":"bad"},"安":{"kanji":"安","level":4,"reading":["アン","やす-い"],"meaning":"cheap"},"以":{"kanji":"以","level":4,"reading":["イ"],"meaning":"by means of"},"医":{"kanji":"医","level":4,"reading":["イ"],"meaning":"medicine"},"意":{"kanji":"意","level":4,"reading":["イ"],"meaning":"idea"},"員":{"kanji":"員","level":4,"reading":["イン"],"meaning":"member"},"院":{"kanji":"院","level":4,"reading":["イン"],"meaning":"institution"},"飲":{"kanji":"飲","level":4,"reading":["イン","の-む"],"meaning":"drink"},"運":{"kanji":"運","level":4,"reading":["ウン","はこ-ぶ"],"meaning":"carry"},"英":{"kanji":"英","level":4,"reading":["エイ"],"meaning":"England"},"映":{"kanji":"映","level":4,"reading":["エイ","うつ-る","うつ-す","は-える"],"meaning":"reflect"},"駅":{"kanji":"駅","level":4,"reading":["エキ"],"meaning":"station"},"屋":{"kanji":"屋","level":4,"reading":["オク","や"],"meaning":"roof"},"音":{"kanji":"音","level":4,"reading":["オン","イン","おと","ね"],"meaning":"sound"},"可":{"kanji":"可","level":4,"reading":["カ"],"meaning":"possible"},"花":{"kanji":"花","level":4,"reading":["カ","はな"],"meaning":"flower"},"夏":{"kanji":"夏","level":4,"reading":["カ","（ゲ）","なつ"],"meaning":"summer"},"家":{"kanji":"家","level":4,"reading":["カ","ケ","いえ","や"],"meaning":"house"},"歌":{"kanji":"歌","level":4,"reading":["カ","うた","うた-う"],"meaning":"song"},"画":{"kanji":"画","level":4,"reading":["ガ","カク"],"meaning":"tableau"},"会":{"kanji":"会","level":4,"reading":["カイ","エ","あ-う"],"meaning":"association"},"海":{"kanji":"海","level":4,"reading":["カイ","うみ"],"meaning":"sea"},"界":{"kanji":"界","level":4,"reading":["カイ"],"meaning":"world"},"開":{"kanji":"開","level":4,"reading":["カイ","ひら-く","ひら-ける","あ-く","あ-ける"],"meaning":"open"},"楽":{"kanji":"楽","level":4,"reading":["ガク","ラク","たの-しい","たの-しむ"],"meaning":"pleasure"},"漢":{"kanji":"漢","level":4,"reading":["カン"],"meaning":"China"},"館":{"kanji":"館","level":4,"reading":["カン","やかた"],"meaning":"public building"},"起":{"kanji":"起","level":4,"reading":["キ","お-きる","お-こる","お-こす"],"meaning":"wake up"},"帰":{"kanji":"帰","level":4,"reading":["キ","かえ-る","かえ-す"],"meaning":"return"},"究":{"kanji":"究","level":4,"reading":["キュウ","きわ-める"],"meaning":"research"},"急":{"kanji":"急","level":4,"reading":["キュウ","いそ-ぐ"],"meaning":"hurry"},"牛":{"kanji":"牛","level":4,"reading":["ギュウ","うし"],"meaning":"cow"},"去":{"kanji":"去","level":4,"reading":["キョ","コ","さ-る"],"meaning":"leave"},"魚":{"kanji":"魚","level":4,"reading":["ギョ","うお","さかな"],"meaning":"fish"},"京":{"kanji":"京","level":4,"reading":["キョウ","ケイ"],"meaning":"capital"},"強":{"kanji":"強","level":4,"reading":["キョウ","ゴウ","つよ-い","つよ-まる","つよ-める","し-いる"],"meaning":"strong"},"教":{"kanji":"教","level":4,"reading":["キョウ","おし-える","おそ-わる"],"meaning":"teach"},"業":{"kanji":"業","level":4,"reading":["ギョウ","ゴウ","わざ"],"meaning":"business"},"近":{"kanji":"近","level":4,"reading":["キン","ちか-い"],"meaning":"near"},"銀":{"kanji":"銀","level":4,"reading":["ギン"],"meaning":"silver"},"空":{"kanji":"空","level":4,"reading":["クウ","そら","あ-く","あ-ける","から"],"meaning":"sky"},"兄":{"kanji":"兄","level":4,"reading":["ケイ","（キョウ）","あに"],"meaning":"older brother"},"計":{"kanji":"計","level":4,"reading":["ケイ","はか-る","はか-らう"],"meaning":"measure"},"犬":{"kanji":"犬","level":4,"reading":["ケン","いぬ"],"meaning":"dog"},"建":{"kanji":"建","level":4,"reading":["ケン","（コン）","た-てる","た-つ"],"meaning":"build"},"研":{"kanji":"研","level":4,"reading":["ケン","と-ぐ"],"meaning":"sharpen"},"験":{"kanji":"験","level":4,"reading":["ケン","（ゲン）"],"meaning":"test"},"元":{"kanji":"元","level":4,"reading":["ゲン","ガン","もと"],"meaning":"origin"},"言":{"kanji":"言","level":4,"reading":["ゲン","ゴン","い-う","こと"],"meaning":"say"},"古":{"kanji":"古","level":4,"reading":["コ","ふる-い","ふる-す"],"meaning":"old"},"口":{"kanji":"口","level":4,"reading":["コウ","ク","くち"],"meaning":"mouth"},"工":{"kanji":"工","level":4,"reading":["コウ","ク"],"meaning":"craft"},"公":{"kanji":"公","level":4,"reading":["コウ","おおやけ"],"meaning":"public"},"広":{"kanji":"広","level":4,"reading":["コウ","ひろ-い","ひろ-まる","ひろ-める","ひろ-がる","ひろ-げる"],"meaning":"wide"},"考":{"kanji":"考","level":4,"reading":["コウ","かんが-える"],"meaning":"think"},"黒":{"kanji":"黒","level":4,"reading":["コク","くろ","くろ-い"],"meaning":"black"},"作":{"kanji":"作","level":4,"reading":["サク","サ","つく-る"],"meaning":"make"},"止":{"kanji":"止","level":4,"reading":["シ","と-まる","と-める"],"meaning":"stop"},"仕":{"kanji":"仕","level":4,"reading":["シ","（ジ）","つか-える"],"meaning":"do"},"死":{"kanji":"死","level":4,"reading":["シ","し-ぬ"],"meaning":"death"},"私":{"kanji":"私","level":4,"reading":["シ","わたくし","わたし"],"meaning":"me"},"使":{"kanji":"使","level":4,"reading":["シ","つか-う"],"meaning":"use"},"始":{"kanji":"始","level":4,"reading":["シ","はじ-める","はじ-まる"],"meaning":"begin"},"姉":{"kanji":"姉","level":4,"reading":["シ","あね"],"meaning":"older sister"},"思":{"kanji":"思","level":4,"reading":["シ","おも-う"],"meaning":"think"},"紙":{"kanji":"紙","level":4,"reading":["シ","かみ"],"meaning":"paper"},"試":{"kanji":"試","level":4,"reading":["シ","こころ-みる","ため-す"],"meaning":"test"},"字":{"kanji":"字","level":4,"reading":["ジ","あざ"],"meaning":"letter"},"自":{"kanji":"自","level":4,"reading":["ジ","シ","みずか-ら"],"meaning":"oneself"},"事":{"kanji":"事","level":4,"reading":["ジ","（ズ）","こと"],"meaning":"abstract thing"},"持":{"kanji":"持","level":4,"reading":["ジ","も-つ"],"meaning":"hold"},"室":{"kanji":"室","level":4,"reading":["シツ","むろ"],"meaning":"room"},"質":{"kanji":"質","level":4,"reading":["シツ","シチ","（チ）"],"meaning":"quality"},"写":{"kanji":"写","level":4,"reading":["シャ","うつ-す","うつ-る"],"meaning":"copy"},"社":{"kanji":"社","level":4,"reading":["シャ","やしろ"],"meaning":"company"},"者":{"kanji":"者","level":4,"reading":["シャ","もの"],"meaning":"someone"},"借":{"kanji":"借","level":4,"reading":["シャク","か-りる"],"meaning":"borrow"},"手":{"kanji":"手","level":4,"reading":["シュ","て","（た）"],"meaning":"hand"},"主":{"kanji":"主","level":4,"reading":["シュ","（ス）","ぬし","おも"],"meaning":"master"},"秋":{"kanji":"秋","level":4,"reading":["シュウ","あき"],"meaning":"autumn"},"終":{"kanji":"終","level":4,"reading":["シュウ","お-わる","お-える"],"meaning":"end"},"習":{"kanji":"習","level":4,"reading":["シュウ","なら-う"],"meaning":"learn"},"週":{"kanji":"週","level":4,"reading":["シュウ"],"meaning":"week"},"集":{"kanji":"集","level":4,"reading":["シュウ","あつ-まる","あつ-める","つど-う"],"meaning":"collect"},"住":{"kanji":"住","level":4,"reading":["ジュウ","す-む","す-まう"],"meaning":"dwelling"},"重":{"kanji":"重","level":4,"reading":["ジュウ","チョウ","え","おも-い","かさ-ねる","かさ-なる"],"meaning":"heavy"},"春":{"kanji":"春","level":4,"reading":["シュン","はる"],"meaning":"springtime"},"少":{"kanji":"少","level":4,"reading":["ショウ","すく-ない","すこ-し"],"meaning":"few"},"場":{"kanji":"場","level":4,"reading":["ジョウ","ば"],"meaning":"place"},"色":{"kanji":"色","level":4,"reading":["ショク","シキ","いろ"],"meaning":"color"},"心":{"kanji":"心","level":4,"reading":["シン","こころ"],"meaning":"heart"},"身":{"kanji":"身","level":4,"reading":["シン","み"],"meaning":"body"},"真":{"kanji":"真","level":4,"reading":["シン","ま"],"meaning":"TRUE"},"新":{"kanji":"新","level":4,"reading":["シン","あたら-しい","あら-た","にい"],"meaning":"new"},"親":{"kanji":"親","level":4,"reading":["シン","おや","した-しい","した-しむ"],"meaning":"parent"},"図":{"kanji":"図","level":4,"reading":["ズ","ト","はか-る"],"meaning":"diagram"},"世":{"kanji":"世","level":4,"reading":["セイ","セ","よ"],"meaning":"world"},"正":{"kanji":"正","level":4,"reading":["セイ","ショウ","ただ-しい","ただ-す","まさ"],"meaning":"correct"},"青":{"kanji":"青","level":4,"reading":["セイ","（ショウ）","あお","あお-い"],"meaning":"blue"},"夕":{"kanji":"夕","level":4,"reading":["セキ","ゆう"],"meaning":"evening"},"赤":{"kanji":"赤","level":4,"reading":["セキ","（シャク）","あか","あか-い","あか-らむ","あか-らめる"],"meaning":"red"},"切":{"kanji":"切","level":4,"reading":["セツ","（サイ）","き-る","き-れる"],"meaning":"cut"},"早":{"kanji":"早","level":4,"reading":["ソウ","（サッ）","はや-い","はや-まる","はや-める"],"meaning":"early"},"走":{"kanji":"走","level":4,"reading":["ソウ","はし-る"],"meaning":"run"},"送":{"kanji":"送","level":4,"reading":["ソウ","おく-る"],"meaning":"send"},"足":{"kanji":"足","level":4,"reading":["ソク","あし","た-りる","た-る","た-す"],"meaning":"foot"},"族":{"kanji":"族","level":4,"reading":["ゾク"],"meaning":"tribe"},"多":{"kanji":"多","level":4,"reading":["タ","おお-い"],"meaning":"many"},"体":{"kanji":"体","level":4,"reading":["タイ","テイ","からだ"],"meaning":"body"},"待":{"kanji":"待","level":4,"reading":["タイ","ま-つ"],"meaning":"wait"},"貸":{"kanji":"貸","level":4,"reading":["タイ","か-す"],"meaning":"lend"},"代":{"kanji":"代","level":4,"reading":["ダイ","タイ","か-わる","か-える","よ","しろ"],"meaning":"substitute"},"台":{"kanji":"台","level":4,"reading":["ダイ","タイ"],"meaning":"pedestal"},"題":{"kanji":"題","level":4,"reading":["ダイ"],"meaning":"topic"},"地":{"kanji":"地","level":4,"reading":["チ","ジ"],"meaning":"ground"},"知":{"kanji":"知","level":4,"reading":["チ","し-る"],"meaning":"know"},"茶":{"kanji":"茶","level":4,"reading":["チャ","サ"],"meaning":"tea"},"着":{"kanji":"着","level":4,"reading":["チャク","（ジャク）","き-る","き-せる","つ-く","つ-ける"],"meaning":"wear"},"注":{"kanji":"注","level":4,"reading":["チュウ","そそ-ぐ"],"meaning":"pour"},"昼":{"kanji":"昼","level":4,"reading":["チュウ","ひる"],"meaning":"daytime"},"町":{"kanji":"町","level":4,"reading":["チョウ","まち"],"meaning":"town"},"鳥":{"kanji":"鳥","level":4,"reading":["チョウ","とり"],"meaning":"bird"},"朝":{"kanji":"朝","level":4,"reading":["チョウ","あさ"],"meaning":"morning"},"通":{"kanji":"通","level":4,"reading":["ツウ","（ツ）","とお-る","とお-す","かよ-う"],"meaning":"pass through"},"弟":{"kanji":"弟","level":4,"reading":["テイ","（ダイ）","（デ）","おとうと"],"meaning":"younger brother"},"的":{"kanji":"的","level":4,"reading":["テキ","まと"],"meaning":"target"},"店":{"kanji":"店","level":4,"reading":["テン","みせ"],"meaning":"shop"},"転":{"kanji":"転","level":4,"reading":["テン","ころ-がる","ころ-げる","ころ-がす","ころ-ぶ"],"meaning":"revolve"},"田":{"kanji":"田","level":4,"reading":["デン","た"],"meaning":"rice paddy"},"度":{"kanji":"度","level":4,"reading":["ド","（ト）","（タク）","たび"],"meaning":"degrees"},"冬":{"kanji":"冬","level":4,"reading":["トウ","ふゆ"],"meaning":"winter"},"答":{"kanji":"答","level":4,"reading":["トウ","こた-える","こた-え"],"meaning":"answer"},"同":{"kanji":"同","level":4,"reading":["ドウ","おな-じ"],"meaning":"same"},"動":{"kanji":"動","level":4,"reading":["ドウ","うご-く","うご-かす"],"meaning":"move"},"堂":{"kanji":"堂","level":4,"reading":["ドウ"],"meaning":"public chamber"},"道":{"kanji":"道","level":4,"reading":["ドウ","（トウ）","みち"],"meaning":"road"},"特":{"kanji":"特","level":4,"reading":["トク"],"meaning":"special"},"肉":{"kanji":"肉","level":4,"reading":["ニク"],"meaning":"meat"},"売":{"kanji":"売","level":4,"reading":["バイ","う-る","う-れる"],"meaning":"sell"},"買":{"kanji":"買","level":4,"reading":["バイ","か-う"],"meaning":"buy"},"発":{"kanji":"発","level":4,"reading":["ハツ","ホツ"],"meaning":"departure"},"飯":{"kanji":"飯","level":4,"reading":["ハン","めし"],"meaning":"meal"},"病":{"kanji":"病","level":4,"reading":["ビョウ","（ヘイ）","や-む","やまい"],"meaning":"sick"},"品":{"kanji":"品","level":4,"reading":["ヒン","しな"],"meaning":"article"},"不":{"kanji":"不","level":4,"reading":["フ","ブ"],"meaning":"non-"},"風":{"kanji":"風","level":4,"reading":["フウ","（フ）","かぜ","（かざ）"],"meaning":"wind"},"服":{"kanji":"服","level":4,"reading":["フク"],"meaning":"clothes"},"物":{"kanji":"物","level":4,"reading":["ブツ","モツ","もの"],"meaning":"thing"},"文":{"kanji":"文","level":4,"reading":["ブン","モン","ふみ"],"meaning":"writing"},"別":{"kanji":"別","level":4,"reading":["ベツ","わか-れる"],"meaning":"separate"},"勉":{"kanji":"勉","level":4,"reading":["ベン"],"meaning":"exertion"},"歩":{"kanji":"歩","level":4,"reading":["ホ","ブ","（フ）","ある-く","あゆ-む"],"meaning":"walk"},"方":{"kanji":"方","level":4,"reading":["ホウ","かた"],"meaning":"direction"},"妹":{"kanji":"妹","level":4,"reading":["マイ","いもうと"],"meaning":"younger sister"},"味":{"kanji":"味","level":4,"reading":["ミ","あじ","あじ-わう"],"meaning":"flavor"},"無":{"kanji":"無","level":4,"reading":["ム","ブ","な-い"],"meaning":"nothing"},"明":{"kanji":"明","level":4,"reading":["メイ","ミョウ","あ-かり","あか-るい","あか-るむ","あか-らむ","あき-らか","あ-ける","あ-く","あ-くる","あ-かす"],"meaning":"bright"},"目":{"kanji":"目","level":4,"reading":["モク","（ボク）","め","（ま）"],"meaning":"eye"},"問":{"kanji":"問","level":4,"reading":["モン","と-う","と-い","（とん）"],"meaning":"question"},"夜":{"kanji":"夜","level":4,"reading":["ヤ","よ","よる"],"meaning":"night"},"野":{"kanji":"野","level":4,"reading":["ヤ","の"],"meaning":"field"},"有":{"kanji":"有","level":4,"reading":["ユウ","ウ","あ-る"],"meaning":"have"},"用":{"kanji":"用","level":4,"reading":["ヨウ","もち-いる"],"meaning":"use"},"洋":{"kanji":"洋","level":4,"reading":["ヨウ"],"meaning":"ocean"},"曜":{"kanji":"曜","level":4,"reading":["ヨウ"],"meaning":"day of the week"},"理":{"kanji":"理","level":4,"reading":["リ"],"meaning":"reason"},"立":{"kanji":"立","level":4,"reading":["リツ","（リュウ）","た-つ","た-てる"],"meaning":"stand up"},"旅":{"kanji":"旅","level":4,"reading":["リョ","たび"],"meaning":"trip"},"料":{"kanji":"料","level":4,"reading":["リョウ"],"meaning":"fee"},"力":{"kanji":"力","level":4,"reading":["リョク","リキ","ちから"],"meaning":"power"}}
